changecode/__init__.py
changecode/baseparse.py
changecode/classes.py
changecode/code.py
changecode/functions.py
changecode/imports.py
changecode-0.0.2.dist-info/LICENSE.md
changecode-0.0.2.dist-info/METADATA
changecode-0.0.2.dist-info/WHEEL
changecode-0.0.2.dist-info/RECORD
