Metadata-Version: 2.1
Name: changecode
Version: 0.0.2
Summary: Change python code
License: MIT
Author: BulatXam
Author-email: Khamdbulat@yandex.ru
Requires-Python: >=3.7
Classifier: License :: OSI Approved :: MIT License
Classifier: Programming Language :: Python :: 3
Classifier: Programming Language :: Python :: 3.7
Classifier: Programming Language :: Python :: 3.8
Classifier: Programming Language :: Python :: 3.9
Classifier: Programming Language :: Python :: 3.10
Classifier: Programming Language :: Python :: 3.11
